design/ahb_slave_demo/rtl/ahb_slave_calc.v
module ahb_slave_calc 
#(parameter WIDTH=32)
(
    input   wire            enable_i,
    input   wire[1:0]       opcode_i,
    input   wire[15:0]      operate_a_i,
    input   wire[15:0]      operate_b_i,
    output  reg[WIDTH-1:0]  operate_res_o
); 

parameter OPCODE_ADD = 2'b00;
parameter OPCODE_SUB = 2'b01;
parameter OPCODE_MUL = 2'b10;
parameter OPCODE_DIV = 2'b11;

always @(*)
begin
  if(enable_i)
    begin
      case(opcode_i)
          OPCODE_ADD:operate_res_o = operate_a_i + operate_b_i;
          OPCODE_SUB:operate_res_o = operate_a_i - operate_b_i;
          OPCODE_MUL:operate_res_o = operate_a_i * operate_b_i;
          OPCODE_DIV:operate_res_o = operate_a_i / operate_b_i;
      endcase
    end
  else
    begin
      operate_res_o = 32'b0;
    end
end 


endmodule

design/ahb_slave_demo/rtl/ahb_slave_if.v
module ahb_slave_if
#(parameter WIDTH=32)
(
    //input
    input   wire                hclk_i,
    input   wire                hresetn_i,
    input   wire                hsel_i,
    input   wire[WIDTH-1:0]     haddr_i,
    input   wire                hwrite_i,
    input   wire[1:0]           htrans_i,
    input   wire[2:0]           hsize_i,
    input   wire[2:0]           hburst_i,
    input   wire[WIDTH-1:0]     hwdata_i,

    input   wire[3:0]           hmaster_i,
    input   wire                hmastlock_i,

    //output 
    output  reg[WIDTH-1:0]      hrdata_o,
    output  wire                hready_o,
    output  wire[1:0]           hresp_o,
    output  wire[15:0]          hsplit_o,

    output   wire               enable_o,
    output   wire[1:0]          opcode_o,
    output   wire[15:0]         operate_a_o,
    output   wire[15:0]         operate_b_o
);

//htrans
parameter IDLE   = 2'b00;
parameter BUSY   = 2'b01;
parameter NONSEQ = 2'b10;
parameter SEQ    = 2'b11;

//addr
`define ENABLE_ADDR     32'h00
`define OPCODE_ADDR     32'h04
`define OPA_ADDR        32'h08
`define OPB_ADDR        32'h0C
`define RES_ADDR        32'h10

//hresp
`define OKAY            2'b00
`define ERROR           2'b01

//local
wire hwrite;
wire hread ;

reg             enable_r;
reg[1:0]        opcode_r;
reg[15:0]       operate_a_r = 16'b0;
reg[15:0]       operate_b_r = 16'b0;
reg[WIDTH-1:0]  res_r;

reg             hwrite_r;
reg[1:0]        htrans_r;
reg[2:0]        hsize_r;
reg[2:0]        hburst_r;
reg[WIDTH-1:0]  haddr_r;

//===========================================================================================
//logic
assign hready_o = 1'b1;
assign hresp_o = `OKAY;

assign hwrite = (hsel_i && hwrite_i && (htrans_i==NONSEQ) || (htrans_i==SEQ));
assign hread  = hsel_i && !hwrite_i && (htrans_i==NONSEQ || htrans_i==SEQ);

assign enable_o = enable_r;
assign opcode_o = opcode_r;
assign operate_a_o = operate_a_r;
assign operate_b_o = operate_b_r;

//sample the master control singles
always @(posedge hclk_i or negedge hresetn_i) 
  begin
    if(!hresetn_i)
      begin
        hwrite_r    <= 1'b0;
        htrans_r    <= 2'b0;
        hsize_r     <= 3'b0;
        hburst_r    <= 3'b0;
        haddr_r     <= 32'b0;
      end
    else if(hsel_i)
      begin
        hwrite_r    <= hwrite_i;
        htrans_r    <= htrans_i;
        hsize_r     <= hsize_i ;
        hburst_r    <= hburst_i;
        haddr_r     <= haddr_i ;
      end
    else
      begin
        hwrite_r    <= 1'b0;
        htrans_r    <= 2'b0;
        hsize_r     <= 3'b0;
        hburst_r    <= 3'b0;
      end
  end

//write or read data
always @(posedge hclk_i or negedge hresetn_i) 
  begin
    if(!hresetn_i)
      begin
            enable_r <= 1'b0;        
            opcode_r <= 2'b00;
            operate_a_r <= 16'b00;
            operate_a_r <= 16'b00;
      end
    else if(hwrite)
      begin
        case(haddr_r) 
          `ENABLE_ADDR:   enable_r    <= hwdata_i[0];
          `OPCODE_ADDR:   opcode_r    <= hwdata_i[1:0];
          `OPA_ADDR:      operate_a_r <= hwdata_i[15:0];
          `OPB_ADDR:      operate_b_r <= hwdata_i[15:0];
        endcase
      end
    else if(hread)
      begin
        case(haddr_r) 
          `ENABLE_ADDR:   hrdata_o  <= {31'b0,enable_r};
          `OPCODE_ADDR:   hrdata_o  <= {30'b0,opcode_r};
          `OPA_ADDR:      hrdata_o  <= {16'b0,operate_a_r};
          `OPB_ADDR:      hrdata_o  <= {16'b0,operate_b_r}; 
        endcase
      end
    else
      begin
        hrdata_o = 32'b0;
      end  

      //$display("%b,%b,%b,%b\n",hwrite, hsel_i, hwrite_i, htrans_i);
  end

endmodule

design/ahb_slave_demo/rtl/ahb_calc_top.v
// `include "ahb_slave_if.v"
// `include "ahb_slave_calc.v"

module ahb_calc_top 
(
    //input
    input   wire           hclk_i,
    input   wire           hresetn_i,
    input   wire           hsel_i,
    input   wire[31:0]     haddr_i,
    input   wire           hwrite_i,
    input   wire[1:0]      htrans_i,
    input   wire[2:0]      hsize_i,
    input   wire[2:0]      hburst_i,
    input   wire[31:0]     hwdata_i,

    input   wire[3:0]      hmaster_i,
    input   wire           hmastlock_i,

    //output 
    output  wire[31:0]     hrdata_o,
    output  wire           hready_o,
    output  wire[1:0]      hresp_o,
    output  wire[15:0]     hsplit_o,
    
    output  wire[31:0]     operate_res
);

//declare
wire            enable;
wire[1:0]       opcode;
wire[15:0]      operate_a;
wire[15:0]      operate_b;


//inst module
ahb_slave_if ahb_slave_if_u1
                            (
                            //input
                            .hclk_i(hclk_i),
                            .hresetn_i(hresetn_i),
                            .hsel_i(hsel_i),
                            .haddr_i(haddr_i),
                            .hwrite_i(hwrite_i),
                            .htrans_i(htrans_i),
                            .hsize_i(hsize_i),
                            .hburst_i(hburst_i),
                            .hwdata_i(hwdata_i),
                            .hmaster_i(hmaster_i),
                            .hmastlock_i(hmastlock_i),
                            .hrdata_o(hrdata_o),
                            .hready_o(hready_o),
                            .hresp_o(hresp_o),
                            .hsplit_o(hsplit_o),
                            .enable_o(enable),
                            .opcode_o(opcode),
                            .operate_a_o(operate_a),
                            .operate_b_o(operate_b)
                            );

ahb_slave_calc ahb_slave_calc_u1
                            (
                            .enable_i(enable),
                            .opcode_i(opcode),
                            .operate_a_i(operate_a),
                            .operate_b_i(operate_b),
                            .operate_res_o(operate_res)
                            );

endmodule //ahb_calc_top

design/ahb_slave_demo/tb/ahb_slave_calc_tb2.v
`timescale 1ns/1ns

module ahb_slave_calc_tb;
reg           hclk = 1'b0;
reg           hresetn;
reg           hsel;
reg[31:0]     haddr;
reg           hwrite;
reg[1:0]      htrans;
reg[2:0]      hsize;
reg[2:0]      hburst;
reg[31:0]     hwdata;
reg[3:0]      hmaster;
reg           hmastlock;
wire[31:0]    hrdata;
wire          hready;
wire[1:0]     hresp;
wire[15:0]    hsplit;

wire[31:0]    operate_res;


//参数定义-HTRANS
parameter IDLE     = 2'b00; 
parameter BUSY     = 2'b01;
parameter NONSEQ   = 2'b10;
parameter SEQ      = 2'b11;

//参数定义-HRESP
parameter OKAY     = 2'b00;
parameter ERROR    = 2'b01;
parameter RETRY    = 2'b10;
parameter SPLIT    = 2'b11;

//参数定义-HBUSRT
parameter SINGLE    = 3'b000;
parameter INCR      = 3'b001;
parameter WRAP4     = 3'b010;
parameter INCR4     = 3'b011;
parameter WRAP8     = 3'b100;
parameter INCR8     = 3'b101;

parameter WRAP16    = 3'b110;
parameter INCR16    = 3'b111;

//local
reg[31:0] read_data=32'h00;

//task
task ahb_write(input [31:0] addr,input [31:0] data);
  begin
    @(posedge hclk);
    #1 
    hresetn   = 1'b1;
    hsel      = 1'b1;
    haddr     = addr;
    hwrite    = 1'b1;
    htrans    = NONSEQ;
    hsize     = 3'b010; //32bits
    hburst    = SINGLE;

    @(posedge hclk);
    #1
    hwdata    = data;
  end 

endtask

task ahb_read(input [31:0] addr,output reg [31:0] data);
  begin
    @(posedge hclk);
    #1 
    hresetn   = 1'b1;
    hsel      = 1'b1;
    haddr     = addr;
    hwrite    = 1'b0;
    htrans    = NONSEQ;
    hsize     = 3'b010; //32bits
    hburst    = SINGLE;

    @(posedge hclk);
    #1
    @(posedge hclk);
    #1
    data      = hrdata;

  end 

endtask

//生成输入激励
//clk generate
always #10 hclk = ~hclk;

initial 
  begin
	  $dumpfile("wave.vcd");  // 指定VCD文件的名字为wave.vcd,仿真信息将记录到此文件
	  $dumpvars(0, ahb_slave_calc_tb );  // 指定层次数为0,则tb_code模块及其下面各层次的所有信号将被记录
  end

//初始化
initial
  begin
    hresetn   = 1'b0;
    hsel      = 1'b0;
    haddr     = 32'b0;
    hwrite    = 1'b0;
    htrans    = IDLE;
    hsize     = 3'b010;//32bits
    hburst    = SINGLE;
    hwdata    = 32'b0;
    hmaster   = 4'b0010;
    hmastlock = 1'b1;
  end

initial
  begin
    //ENABLE_ADDR
    ahb_write(32'b00,32'b1);

    //OPCODE_ADDR,OPCODE_MUL
    ahb_write(32'h04,32'b10);
   
    //OPA_ADDR
    ahb_write(32'h08,32'h3);

    //OPB_ADDR
    ahb_write(32'h0C,32'h4);

    @(posedge hclk);
    #1
    $display("%h * %h = %h\n",3,4,operate_res);

    //OPA_ADDR
    ahb_read(32'h08,read_data);
  
    @(posedge hclk);
    #1
    $display("opa:%h\n",read_data);
    $finish();

  end

ahb_calc_top ahb_calc_top_u1
                        (
                        .hclk_i(hclk),
                        .hresetn_i(hresetn),
                        .hsel_i(hsel),
                        .haddr_i(haddr),
                        .hwrite_i(hwrite),
                        .htrans_i(htrans),
                        .hsize_i(hsize),
                        .hburst_i(hburst),
                        .hwdata_i(hwdata),
                        .hmaster_i(hmaster),
                        .hmastlock_i(hmastlock),
                        .hrdata_o(hrdata),
                        .hready_o(hready),
                        .hresp_o(hresp),
                        .hsplit_o(hsplit),
                        .operate_res(operate_res)
                        );

endmodule //ahb_slave_calc_tb

design/ahb_slave_demo/build/build_out/wave.vcd
$date
	Mon Jan 11 09:11:54 2021
$end
$version
	Icarus Verilog
$end
$timescale
	1ns
$end
$scope module ahb_slave_calc_tb $end
$var wire 1 ! hready $end
$var wire 2 " hresp [1:0] $end
$var wire 16 # hsplit [15:0] $end
$var wire 32 $ operate_res [31:0] $end
$var wire 32 % hrdata [31:0] $end
$var reg 32 & haddr [31:0] $end
$var reg 3 ' hburst [2:0] $end
$var reg 1 ( hclk $end
$var reg 4 ) hmaster [3:0] $end
$var reg 1 * hmastlock $end
$var reg 1 + hresetn $end
$var reg 1 , hsel $end
$var reg 3 - hsize [2:0] $end
$var reg 2 . htrans [1:0] $end
$var reg 32 / hwdata [31:0] $end
$var reg 1 0 hwrite $end
$var reg 32 1 read_data [31:0] $end
$scope module ahb_calc_top_u1 $end
$var wire 32 2 haddr_i [31:0] $end
$var wire 3 3 hburst_i [2:0] $end
$var wire 1 ( hclk_i $end
$var wire 4 4 hmaster_i [3:0] $end
$var wire 1 * hmastlock_i $end
$var wire 1 ! hready_o $end
$var wire 1 + hresetn_i $end
$var wire 2 5 hresp_o [1:0] $end
$var wire 1 , hsel_i $end
$var wire 3 6 hsize_i [2:0] $end
$var wire 16 7 hsplit_o [15:0] $end
$var wire 2 8 htrans_i [1:0] $end
$var wire 32 9 hwdata_i [31:0] $end
$var wire 1 0 hwrite_i $end
$var wire 32 : operate_res [31:0] $end
$var wire 16 ; operate_b [15:0] $end
$var wire 16 < operate_a [15:0] $end
$var wire 2 = opcode [1:0] $end
$var wire 32 > hrdata_o [31:0] $end
$var wire 1 ? enable $end
$scope module ahb_slave_calc_u1 $end
$var wire 16 @ operate_b_i [15:0] $end
$var wire 16 A operate_a_i [15:0] $end
$var wire 2 B opcode_i [1:0] $end
$var wire 1 ? enable_i $end
$var reg 32 C operate_res_o [31:0] $end
$upscope $end
$scope module ahb_slave_if_u1 $end
$var wire 1 ? enable_o $end
$var wire 32 D haddr_i [31:0] $end
$var wire 3 E hburst_i [2:0] $end
$var wire 1 ( hclk_i $end
$var wire 4 F hmaster_i [3:0] $end
$var wire 1 * hmastlock_i $end
$var wire 1 G hread $end
$var wire 1 ! hready_o $end
$var wire 1 + hresetn_i $end
$var wire 2 H hresp_o [1:0] $end
$var wire 1 , hsel_i $end
$var wire 3 I hsize_i [2:0] $end
$var wire 16 J hsplit_o [15:0] $end
$var wire 2 K htrans_i [1:0] $end
$var wire 32 L hwdata_i [31:0] $end
$var wire 1 M hwrite $end
$var wire 1 0 hwrite_i $end
$var wire 2 N opcode_o [1:0] $end
$var wire 16 O operate_a_o [15:0] $end
$var wire 16 P operate_b_o [15:0] $end
$var reg 1 Q enable_r $end
$var reg 32 R haddr_r [31:0] $end
$var reg 3 S hburst_r [2:0] $end
$var reg 32 T hrdata_o [31:0] $end
$var reg 3 U hsize_r [2:0] $end
$var reg 2 V htrans_r [1:0] $end
$var reg 1 W hwrite_r $end
$var reg 2 X opcode_r [1:0] $end
$var reg 16 Y operate_a_r [15:0] $end
$var reg 16 Z operate_b_r [15:0] $end
$upscope $end
$upscope $end
$scope task ahb_read $end
$var reg 32 [ addr [31:0] $end
$var reg 32 \ data [31:0] $end
$upscope $end
$scope task ahb_write $end
$var reg 32 ] addr [31:0] $end
$var reg 32 ^ data [31:0] $end
$upscope $end
$upscope $end
$enddefinitions $end
#0
$dumpvars
b1 ^
b0 ]
bx \
bx [
b0 Z
b0 Y
b0 X
0W
b0 V
b0 U
bx T
b0 S
b0 R
0Q
b0 P
b0 O
b0 N
0M
b0 L
b0 K
bz J
b10 I
b0 H
0G
b10 F
b0 E
b0 D
b0 C
b0 B
b0 A
b0 @
0?
bx >
b0 =
b0 <
b0 ;
b0 :
b0 9
b0 8
bz 7
b10 6
b0 5
b10 4
b0 3
b0 2
b0 1
00
b0 /
b0 .
b10 -
0,
0+
1*
b10 )
0(
b0 '
b0 &
bx %
b0 $
bz #
b0 "
1!
$end
#10
1(
#11
1M
b10 .
b10 8
b10 K
10
1,
1+
#20
0(
#30
b10 U
b10 V
1W
1(
#31
b10 ^
b100 ]
b1 /
b1 9
b1 L
#40
0(
#50
1?
1Q
1(
#51
b100 &
b100 2
b100 D
#60
0(
#70
b100 R
1(
#71
b11 ^
b1000 ]
b10 /
b10 9
b10 L
#80
0(
#90
b10 =
b10 B
b10 N
b10 X
1(
#91
b1000 &
b1000 2
b1000 D
#100
0(
#110
b1000 R
1(
#111
b100 ^
b1100 ]
b11 /
b11 9
b11 L
#120
0(
#130
b11 <
b11 A
b11 O
b11 Y
1(
#131
b1100 &
b1100 2
b1100 D
#140
0(
#150
b1100 R
1(
#151
b100 /
b100 9
b100 L
#160
0(
#170
b1100 $
b1100 :
b1100 C
b100 ;
b100 @
b100 P
b100 Z
1(
#171
b1000 [
#180
0(
#190
1(
#191
0M
1G
00
b1000 &
b1000 2
b1000 D
#200
0(
#210
b100 %
b100 >
b100 T
b1000 R
0W
1(
#220
0(
#230
b11 %
b11 >
b11 T
1(
#231
b11 1
b11 \
